README.md
setup.py
Hyperbo/Hyperbo.py
Hyperbo/__init__.py
Hyperbo/test_Hyperbo.py
Hyperbo.egg-info/PKG-INFO
Hyperbo.egg-info/SOURCES.txt
Hyperbo.egg-info/dependency_links.txt
Hyperbo.egg-info/top_level.txt